happyserial/BreakfastSerial.py
happyserial/Crc.py
happyserial/HappySerial.py
happyserial/HappyVersion.py
happyserial/Hdlc.py
happyserial/__init__.py
happyserial-1.2.0.dist-info/METADATA
happyserial-1.2.0.dist-info/WHEEL
happyserial-1.2.0.dist-info/top_level.txt
happyserial-1.2.0.dist-info/RECORD
