Metadata-Version: 2.1
Name: happyserial
Version: 1.2.0
Summary: DMA-based framing for serial interaction with an nRF chip
Author: Thomas Watteyne
Author-email: twatteyne@gmail.com
Project-URL: Source Code, https://github.com/openwsn-berkeley/happyserial/
Project-URL: Bug Tracker, https://github.com/openwsn-berkeley/happyserial/issues
Classifier: Programming Language :: Python :: 3
Classifier: License :: OSI Approved :: BSD License
Classifier: Operating System :: OS Independent
Requires-Dist: pyserial
